readmdict/__init__.py
readmdict/__main__.py
readmdict/pureSalsa20.py
readmdict/readmdict.py
readmdict/ripemd128.py
readmdict-0.1.1.dist-info/entry_points.txt
readmdict-0.1.1.dist-info/WHEEL
readmdict-0.1.1.dist-info/METADATA
readmdict-0.1.1.dist-info/RECORD
